xgen/__init__.py
xgen/_logging.py
xgen-0.0.2.dist-info/METADATA
xgen-0.0.2.dist-info/WHEEL
xgen-0.0.2.dist-info/licenses/LICENSE
xgen-0.0.2.dist-info/RECORD
