Metadata-Version: 2.3
Name: xgen
Version: 0.0.2
Summary: the super duper tool for building with llm
Requires-Python: >=3.9
Requires-Dist: instructor>=1.7.0
Requires-Dist: litellm>=1.54.1
Requires-Dist: rich>=13.9.4
